[
  {
    "time": 0.0,
    "proposal": "D3->T0",
    "baseline": {
      "makespan": 1.1099019513592785,
      "t_current": 0.0,
      "t_committed": 0.0,
      "t_inevitable": 0.00078125,
      "t_max_deploy_total": 0.00078125,
      "k_search": 15,
      "uncovered_count": 60,
      "t_remaining_search": 1.1099019513592785,
      "t_finish_search": 1.1099019513592785,
      "bottleneck": "search"
    },
    "after_action": {
      "makespan": 1.2099019513592784,
      "t_current": 0.0,
      "t_committed": 0.0,
      "t_inevitable": 0.0,
      "t_max_deploy_total": 0.0,
      "k_search": 14,
      "uncovered_count": 60,
      "t_remaining_search": 1.2099019513592784,
      "t_finish_search": 1.2099019513592784,
      "bottleneck": "search"
    },
    "utility": -0.09999999999999987,
    "threshold": 0.02219803902718557,
    "decision": "reject"
  },
  {
    "time": 0.1,
    "proposal": "D3->T0",
    "baseline": {
      "makespan": 1.012310562561766,
      "t_current": 0.1,
      "t_committed": 0.0,
      "t_inevitable": 0.20054174544996223,
      "t_max_deploy_total": 0.20054174544996223,
      "k_search": 15,
      "uncovered_count": 56,
      "t_remaining_search": 0.9123105625617661,
      "t_finish_search": 1.012310562561766,
      "bottleneck": "search"
    },
    "after_action": {
      "makespan": 1.060555127546399,
      "t_current": 0.1,
      "t_committed": 0.2,
      "t_inevitable": 0.1237543684304856,
      "t_max_deploy_total": 0.2,
      "k_search": 14,
      "uncovered_count": 56,
      "t_remaining_search": 0.9605551275463989,
      "t_finish_search": 1.060555127546399,
      "bottleneck": "search"
    },
    "utility": -0.04824456498463281,
    "threshold": 0.02024621125123532,
    "decision": "reject"
  },
  {
    "time": 0.1,
    "proposal": "D0->T13",
    "baseline": {
      "makespan": 1.012310562561766,
      "t_current": 0.1,
      "t_committed": 0.0,
      "t_inevitable": 0.20054174544996223,
      "t_max_deploy_total": 0.20054174544996223,
      "k_search": 15,
      "uncovered_count": 56,
      "t_remaining_search": 0.9123105625617661,
      "t_finish_search": 1.012310562561766,
      "bottleneck": "search"
    },
    "after_action": {
      "makespan": 1.165685424949238,
      "t_current": 0.1,
      "t_committed": 0.1447213595499958,
      "t_inevitable": 0.20054174544996223,
      "t_max_deploy_total": 0.20054174544996223,
      "k_search": 14,
      "uncovered_count": 56,
      "t_remaining_search": 1.065685424949238,
      "t_finish_search": 1.165685424949238,
      "bottleneck": "search"
    },
    "utility": -0.153374862387472,
    "threshold": 0.02024621125123532,
    "decision": "reject"
  },
  {
    "time": 0.1,
    "proposal": "D1->T4",
    "baseline": {
      "makespan": 1.012310562561766,
      "t_current": 0.1,
      "t_committed": 0.0,
      "t_inevitable": 0.20054174544996223,
      "t_max_deploy_total": 0.20054174544996223,
      "k_search": 15,
      "uncovered_count": 56,
      "t_remaining_search": 0.9123105625617661,
      "t_finish_search": 1.012310562561766,
      "bottleneck": "search"
    },
    "after_action": {
      "makespan": 1.1414213562373097,
      "t_current": 0.1,
      "t_committed": 0.1,
      "t_inevitable": 0.20044836617674838,
      "t_max_deploy_total": 0.20044836617674838,
      "k_search": 14,
      "uncovered_count": 56,
      "t_remaining_search": 1.0414213562373096,
      "t_finish_search": 1.1414213562373097,
      "bottleneck": "search"
    },
    "utility": -0.12911079367554357,
    "threshold": 0.02024621125123532,
    "decision": "reject"
  },
  {
    "time": 0.2,
    "proposal": "D3->T0",
    "baseline": {
      "makespan": 1.0414213562373096,
      "t_current": 0.2,
      "t_committed": 0.0,
      "t_inevitable": 0.34169756982371047,
      "t_max_deploy_total": 0.34169756982371047,
      "k_search": 15,
      "uncovered_count": 50,
      "t_remaining_search": 0.8414213562373096,
      "t_finish_search": 1.0414213562373096,
      "bottleneck": "search"
    },
    "after_action": {
      "makespan": 1.0327166834558612,
      "t_current": 0.2,
      "t_committed": 0.3414213562373095,
      "t_inevitable": 0.3002655318635612,
      "t_max_deploy_total": 0.3414213562373095,
      "k_search": 14,
      "uncovered_count": 50,
      "t_remaining_search": 0.8327166834558613,
      "t_finish_search": 1.0327166834558612,
      "bottleneck": "search"
    },
    "utility": 0.008704672781448375,
    "threshold": 0.020828427124746193,
    "decision": "reject"
  },
  {
    "time": 0.2,
    "proposal": "D1->T4",
    "baseline": {
      "makespan": 1.0414213562373096,
      "t_current": 0.2,
      "t_committed": 0.0,
      "t_inevitable": 0.34169756982371047,
      "t_max_deploy_total": 0.34169756982371047,
      "k_search": 15,
      "uncovered_count": 50,
      "t_remaining_search": 0.8414213562373096,
      "t_finish_search": 1.0414213562373096,
      "bottleneck": "search"
    },
    "after_action": {
      "makespan": 1.0071067811865475,
      "t_current": 0.2,
      "t_committed": 0.30000000000000004,
      "t_inevitable": 0.34169756982371047,
      "t_max_deploy_total": 0.34169756982371047,
      "k_search": 14,
      "uncovered_count": 50,
      "t_remaining_search": 0.8071067811865476,
      "t_finish_search": 1.0071067811865475,
      "bottleneck": "search"
    },
    "utility": 0.034314575050762075,
    "threshold": 0.020828427124746193,
    "decision": "accept"
  },
  {
    "time": 0.2,
    "proposal": "D0->T13",
    "baseline": {
      "makespan": 1.0414213562373096,
      "t_current": 0.2,
      "t_committed": 0.0,
      "t_inevitable": 0.34169756982371047,
      "t_max_deploy_total": 0.34169756982371047,
      "k_search": 15,
      "uncovered_count": 50,
      "t_remaining_search": 0.8414213562373096,
      "t_finish_search": 1.0414213562373096,
      "bottleneck": "search"
    },
    "after_action": {
      "makespan": 1.0071067811865475,
      "t_current": 0.2,
      "t_committed": 0.30000000000000004,
      "t_inevitable": 0.34169756982371047,
      "t_max_deploy_total": 0.34169756982371047,
      "k_search": 13,
      "uncovered_count": 50,
      "t_remaining_search": 0.8071067811865476,
      "t_finish_search": 1.0071067811865475,
      "bottleneck": "search"
    },
    "utility": 0.0,
    "threshold": 0.02014213562373095,
    "decision": "reject"
  },
  {
    "time": 0.2,
    "proposal": "D7->T6",
    "baseline": {
      "makespan": 1.0414213562373096,
      "t_current": 0.2,
      "t_committed": 0.0,
      "t_inevitable": 0.34169756982371047,
      "t_max_deploy_total": 0.34169756982371047,
      "k_search": 15,
      "uncovered_count": 50,
      "t_remaining_search": 0.8414213562373096,
      "t_finish_search": 1.0414213562373096,
      "bottleneck": "search"
    },
    "after_action": {
      "makespan": 1.140312423743285,
      "t_current": 0.2,
      "t_committed": 0.30000000000000004,
      "t_inevitable": 0.341796875,
      "t_max_deploy_total": 0.341796875,
      "k_search": 13,
      "uncovered_count": 50,
      "t_remaining_search": 0.9403124237432848,
      "t_finish_search": 1.140312423743285,
      "bottleneck": "search"
    },
    "utility": -0.1332056425567374,
    "threshold": 0.02014213562373095,
    "decision": "reject"
  },
  {
    "time": 0.30000000000000004,
    "proposal": "D3->T0",
    "baseline": {
      "makespan": 0.9845313934559851,
      "t_current": 0.30000000000000004,
      "t_committed": 0.30000000000000004,
      "t_inevitable": 0.5421875,
      "t_max_deploy_total": 0.5421875,
      "k_search": 14,
      "uncovered_count": 44,
      "t_remaining_search": 0.684531393455985,
      "t_finish_search": 0.9845313934559851,
      "bottleneck": "search"
    },
    "after_action": {
      "makespan": 1.0,
      "t_current": 0.30000000000000004,
      "t_committed": 0.5414213562373096,
      "t_inevitable": 0.40058593750000004,
      "t_max_deploy_total": 0.5414213562373096,
      "k_search": 13,
      "uncovered_count": 44,
      "t_remaining_search": 0.7,
      "t_finish_search": 1.0,
      "bottleneck": "search"
    },
    "utility": -0.01546860654401494,
    "threshold": 0.019690627869119702,
    "decision": "reject"
  },
  {
    "time": 0.30000000000000004,
    "proposal": "D4->T6",
    "baseline": {
      "makespan": 0.9845313934559851,
      "t_current": 0.30000000000000004,
      "t_committed": 0.30000000000000004,
      "t_inevitable": 0.5421875,
      "t_max_deploy_total": 0.5421875,
      "k_search": 14,
      "uncovered_count": 44,
      "t_remaining_search": 0.684531393455985,
      "t_finish_search": 0.9845313934559851,
      "bottleneck": "search"
    },
    "after_action": {
      "makespan": 1.0656854249492382,
      "t_current": 0.30000000000000004,
      "t_committed": 0.5242942918554048,
      "t_inevitable": 0.5421875,
      "t_max_deploy_total": 0.5421875,
      "k_search": 13,
      "uncovered_count": 44,
      "t_remaining_search": 0.7656854249492381,
      "t_finish_search": 1.0656854249492382,
      "bottleneck": "search"
    },
    "utility": -0.08115403149325318,
    "threshold": 0.019690627869119702,
    "decision": "reject"
  },
  {
    "time": 0.30000000000000004,
    "proposal": "D2->T13",
    "baseline": {
      "makespan": 0.9845313934559851,
      "t_current": 0.30000000000000004,
      "t_committed": 0.30000000000000004,
      "t_inevitable": 0.5421875,
      "t_max_deploy_total": 0.5421875,
      "k_search": 14,
      "uncovered_count": 44,
      "t_remaining_search": 0.684531393455985,
      "t_finish_search": 0.9845313934559851,
      "bottleneck": "search"
    },
    "after_action": {
      "makespan": 0.9845313934559851,
      "t_current": 0.30000000000000004,
      "t_committed": 0.523606797749979,
      "t_inevitable": 0.5417826757745218,
      "t_max_deploy_total": 0.5417826757745218,
      "k_search": 13,
      "uncovered_count": 44,
      "t_remaining_search": 0.684531393455985,
      "t_finish_search": 0.9845313934559851,
      "bottleneck": "search"
    },
    "utility": 0.0,
    "threshold": 0.019690627869119702,
    "decision": "reject"
  },
  {
    "time": 0.30000000000000004,
    "proposal": "D0->T9",
    "baseline": {
      "makespan": 0.9845313934559851,
      "t_current": 0.30000000000000004,
      "t_committed": 0.30000000000000004,
      "t_inevitable": 0.5421875,
      "t_max_deploy_total": 0.5421875,
      "k_search": 14,
      "uncovered_count": 44,
      "t_remaining_search": 0.684531393455985,
      "t_finish_search": 0.9845313934559851,
      "bottleneck": "search"
    },
    "after_action": {
      "makespan": 1.123606797749979,
      "t_current": 0.30000000000000004,
      "t_committed": 0.35436643575176247,
      "t_inevitable": 0.5421875,
      "t_max_deploy_total": 0.5421875,
      "k_search": 13,
      "uncovered_count": 44,
      "t_remaining_search": 0.823606797749979,
      "t_finish_search": 1.123606797749979,
      "bottleneck": "search"
    },
    "utility": -0.139075404293994,
    "threshold": 0.019690627869119702,
    "decision": "reject"
  },
  {
    "time": 0.4,
    "proposal": "D3->T0",
    "baseline": {
      "makespan": 0.9869758240174212,
      "t_current": 0.4,
      "t_committed": 0.30000000000000004,
      "t_inevitable": 0.741796875,
      "t_max_deploy_total": 0.741796875,
      "k_search": 14,
      "uncovered_count": 39,
      "t_remaining_search": 0.5869758240174212,
      "t_finish_search": 0.9869758240174212,
      "bottleneck": "search"
    },
    "after_action": {
      "makespan": 1.0414213562373096,
      "t_current": 0.4,
      "t_committed": 0.7414213562373095,
      "t_inevitable": 0.6006252053518226,
      "t_max_deploy_total": 0.7414213562373095,
      "k_search": 13,
      "uncovered_count": 39,
      "t_remaining_search": 0.6414213562373094,
      "t_finish_search": 1.0414213562373096,
      "bottleneck": "search"
    },
    "utility": -0.05444553221988835,
    "threshold": 0.019739516480348426,
    "decision": "reject"
  },
  {
    "time": 0.4,
    "proposal": "D4->T6",
    "baseline": {
      "makespan": 0.9869758240174212,
      "t_current": 0.4,
      "t_committed": 0.30000000000000004,
      "t_inevitable": 0.741796875,
      "t_max_deploy_total": 0.741796875,
      "k_search": 14,
      "uncovered_count": 39,
      "t_remaining_search": 0.5869758240174212,
      "t_finish_search": 0.9869758240174212,
      "bottleneck": "search"
    },
    "after_action": {
      "makespan": 1.0054080917984929,
      "t_current": 0.4,
      "t_committed": 0.7006408350484792,
      "t_inevitable": 0.741796875,
      "t_max_deploy_total": 0.741796875,
      "k_search": 13,
      "uncovered_count": 39,
      "t_remaining_search": 0.6054080917984928,
      "t_finish_search": 1.0054080917984929,
      "bottleneck": "search"
    },
    "utility": -0.018432267781071654,
    "threshold": 0.019739516480348426,
    "decision": "reject"
  },
  {
    "time": 0.4,
    "proposal": "D2->T13",
    "baseline": {
      "makespan": 0.9869758240174212,
      "t_current": 0.4,
      "t_committed": 0.30000000000000004,
      "t_inevitable": 0.741796875,
      "t_max_deploy_total": 0.741796875,
      "k_search": 14,
      "uncovered_count": 39,
      "t_remaining_search": 0.5869758240174212,
      "t_finish_search": 0.9869758240174212,
      "bottleneck": "search"
    },
    "after_action": {
      "makespan": 1.0530733729460358,
      "t_current": 0.4,
      "t_committed": 0.6000000000000001,
      "t_inevitable": 0.741796875,
      "t_max_deploy_total": 0.741796875,
      "k_search": 13,
      "uncovered_count": 39,
      "t_remaining_search": 0.6530733729460358,
      "t_finish_search": 1.0530733729460358,
      "bottleneck": "search"
    },
    "utility": -0.06609754892861452,
    "threshold": 0.019739516480348426,
    "decision": "reject"
  },
  {
    "time": 0.4,
    "proposal": "D0->T9",
    "baseline": {
      "makespan": 0.9869758240174212,
      "t_current": 0.4,
      "t_committed": 0.30000000000000004,
      "t_inevitable": 0.741796875,
      "t_max_deploy_total": 0.741796875,
      "k_search": 14,
      "uncovered_count": 39,
      "t_remaining_search": 0.5869758240174212,
      "t_finish_search": 0.9869758240174212,
      "bottleneck": "search"
    },
    "after_action": {
      "makespan": 1.0486431106408451,
      "t_current": 0.4,
      "t_committed": 0.4889461560310564,
      "t_inevitable": 0.741796875,
      "t_max_deploy_total": 0.741796875,
      "k_search": 13,
      "uncovered_count": 39,
      "t_remaining_search": 0.6486431106408451,
      "t_finish_search": 1.0486431106408451,
      "bottleneck": "search"
    },
    "utility": -0.06166728662342391,
    "threshold": 0.019739516480348426,
    "decision": "reject"
  },
  {
    "time": 0.4,
    "proposal": "D5->T14",
    "baseline": {
      "makespan": 0.9869758240174212,
      "t_current": 0.4,
      "t_committed": 0.30000000000000004,
      "t_inevitable": 0.741796875,
      "t_max_deploy_total": 0.741796875,
      "k_search": 14,
      "uncovered_count": 39,
      "t_remaining_search": 0.5869758240174212,
      "t_finish_search": 0.9869758240174212,
      "bottleneck": "search"
    },
    "after_action": {
      "makespan": 1.0486431106408451,
      "t_current": 0.4,
      "t_committed": 0.4070193094490059,
      "t_inevitable": 0.741796875,
      "t_max_deploy_total": 0.741796875,
      "k_search": 13,
      "uncovered_count": 39,
      "t_remaining_search": 0.6486431106408451,
      "t_finish_search": 1.0486431106408451,
      "bottleneck": "search"
    },
    "utility": -0.06166728662342391,
    "threshold": 0.019739516480348426,
    "decision": "reject"
  },
  {
    "time": 0.6,
    "proposal": "D3->T0",
    "baseline": {
      "makespan": 1.1419310565187524,
      "t_current": 0.6,
      "t_committed": 0.30000000000000004,
      "t_inevitable": 1.1419310565187524,
      "t_max_deploy_total": 1.1419310565187524,
      "k_search": 14,
      "uncovered_count": 24,
      "t_remaining_search": 0.40098923871549036,
      "t_finish_search": 1.0009892387154904,
      "bottleneck": "deploy"
    },
    "after_action": {
      "makespan": 1.1414213562373094,
      "t_current": 0.6,
      "t_committed": 1.1414213562373094,
      "t_inevitable": 0.9612873710125016,
      "t_max_deploy_total": 1.1414213562373094,
      "k_search": 13,
      "uncovered_count": 24,
      "t_remaining_search": 0.40098923871549036,
      "t_finish_search": 1.0009892387154904,
      "bottleneck": "deploy"
    },
    "utility": 0.0005097002814429263,
    "threshold": 0.022838621130375047,
    "decision": "reject"
  },
  {
    "time": 0.6,
    "proposal": "D4->T2",
    "baseline": {
      "makespan": 1.1419310565187524,
      "t_current": 0.6,
      "t_committed": 0.30000000000000004,
      "t_inevitable": 1.1419310565187524,
      "t_max_deploy_total": 1.1419310565187524,
      "k_search": 14,
      "uncovered_count": 24,
      "t_remaining_search": 0.40098923871549036,
      "t_finish_search": 1.0009892387154904,
      "bottleneck": "deploy"
    },
    "after_action": {
      "makespan": 1.14208984375,
      "t_current": 0.6,
      "t_committed": 1.0056978081638022,
      "t_inevitable": 1.14208984375,
      "t_max_deploy_total": 1.14208984375,
      "k_search": 13,
      "uncovered_count": 24,
      "t_remaining_search": 0.4176210281856127,
      "t_finish_search": 1.0176210281856126,
      "bottleneck": "deploy"
    },
    "utility": -0.00015878723124762573,
    "threshold": 0.022838621130375047,
    "decision": "reject"
  },
  {
    "time": 0.6,
    "proposal": "D2->T13",
    "baseline": {
      "makespan": 1.1419310565187524,
      "t_current": 0.6,
      "t_committed": 0.30000000000000004,
      "t_inevitable": 1.1419310565187524,
      "t_max_deploy_total": 1.1419310565187524,
      "k_search": 14,
      "uncovered_count": 24,
      "t_remaining_search": 0.40098923871549036,
      "t_finish_search": 1.0009892387154904,
      "bottleneck": "deploy"
    },
    "after_action": {
      "makespan": 1.141530983388059,
      "t_current": 0.6,
      "t_committed": 1.0,
      "t_inevitable": 1.141530983388059,
      "t_max_deploy_total": 1.141530983388059,
      "k_search": 13,
      "uncovered_count": 24,
      "t_remaining_search": 0.4104648845664635,
      "t_finish_search": 1.0104648845664634,
      "bottleneck": "deploy"
    },
    "utility": 0.00040007313069345685,
    "threshold": 0.022838621130375047,
    "decision": "reject"
  },
  {
    "time": 0.6,
    "proposal": "D7->T6",
    "baseline": {
      "makespan": 1.1419310565187524,
      "t_current": 0.6,
      "t_committed": 0.30000000000000004,
      "t_inevitable": 1.1419310565187524,
      "t_max_deploy_total": 1.1419310565187524,
      "k_search": 14,
      "uncovered_count": 24,
      "t_remaining_search": 0.40098923871549036,
      "t_finish_search": 1.0009892387154904,
      "bottleneck": "deploy"
    },
    "after_action": {
      "makespan": 1.1419310565187524,
      "t_current": 0.6,
      "t_committed": 0.9605551275463988,
      "t_inevitable": 1.1419310565187524,
      "t_max_deploy_total": 1.1419310565187524,
      "k_search": 13,
      "uncovered_count": 24,
      "t_remaining_search": 0.5075268099434128,
      "t_finish_search": 1.1075268099434128,
      "bottleneck": "deploy"
    },
    "utility": 0.0,
    "threshold": 0.022838621130375047,
    "decision": "reject"
  },
  {
    "time": 0.6,
    "proposal": "D0->T9",
    "baseline": {
      "makespan": 1.1419310565187524,
      "t_current": 0.6,
      "t_committed": 0.30000000000000004,
      "t_inevitable": 1.1419310565187524,
      "t_max_deploy_total": 1.1419310565187524,
      "k_search": 14,
      "uncovered_count": 24,
      "t_remaining_search": 0.40098923871549036,
      "t_finish_search": 1.0009892387154904,
      "bottleneck": "deploy"
    },
    "after_action": {
      "makespan": 1.1419310565187524,
      "t_current": 0.6,
      "t_committed": 0.8789674485408684,
      "t_inevitable": 1.1419310565187524,
      "t_max_deploy_total": 1.1419310565187524,
      "k_search": 13,
      "uncovered_count": 24,
      "t_remaining_search": 0.40465000566845566,
      "t_finish_search": 1.0046500056684557,
      "bottleneck": "deploy"
    },
    "utility": 0.0,
    "threshold": 0.022838621130375047,
    "decision": "reject"
  },
  {
    "time": 0.6,
    "proposal": "D5->T14",
    "baseline": {
      "makespan": 1.1419310565187524,
      "t_current": 0.6,
      "t_committed": 0.30000000000000004,
      "t_inevitable": 1.1419310565187524,
      "t_max_deploy_total": 1.1419310565187524,
      "k_search": 14,
      "uncovered_count": 24,
      "t_remaining_search": 0.40098923871549036,
      "t_finish_search": 1.0009892387154904,
      "bottleneck": "deploy"
    },
    "after_action": {
      "makespan": 1.1419310565187524,
      "t_current": 0.6,
      "t_committed": 0.7990895461140677,
      "t_inevitable": 1.1419310565187524,
      "t_max_deploy_total": 1.1419310565187524,
      "k_search": 13,
      "uncovered_count": 24,
      "t_remaining_search": 0.40098923871549036,
      "t_finish_search": 1.0009892387154904,
      "bottleneck": "deploy"
    },
    "utility": 0.0,
    "threshold": 0.022838621130375047,
    "decision": "reject"
  },
  {
    "time": 0.7,
    "proposal": "D10->T0",
    "baseline": {
      "makespan": 1.2393073369060974,
      "t_current": 0.7,
      "t_committed": 0.30000000000000004,
      "t_inevitable": 1.2393073369060974,
      "t_max_deploy_total": 1.2393073369060974,
      "k_search": 13,
      "uncovered_count": 18,
      "t_remaining_search": 0.423606797749979,
      "t_finish_search": 1.123606797749979,
      "bottleneck": "deploy"
    },
    "after_action": {
      "makespan": 1.2385164807134503,
      "t_current": 0.7,
      "t_committed": 1.2385164807134503,
      "t_inevitable": 1.061038801501411,
      "t_max_deploy_total": 1.2385164807134503,
      "k_search": 12,
      "uncovered_count": 18,
      "t_remaining_search": 0.423606797749979,
      "t_finish_search": 1.123606797749979,
      "bottleneck": "deploy"
    },
    "utility": 0.0007908561926470714,
    "threshold": 0.024786146738121947,
    "decision": "reject"
  },
  {
    "time": 0.7,
    "proposal": "D3->T2",
    "baseline": {
      "makespan": 1.2393073369060974,
      "t_current": 0.7,
      "t_committed": 0.30000000000000004,
      "t_inevitable": 1.2393073369060974,
      "t_max_deploy_total": 1.2393073369060974,
      "k_search": 13,
      "uncovered_count": 18,
      "t_remaining_search": 0.423606797749979,
      "t_finish_search": 1.123606797749979,
      "bottleneck": "deploy"
    },
    "after_action": {
      "makespan": 1.2392550854279274,
      "t_current": 0.7,
      "t_committed": 1.2161846659934081,
      "t_inevitable": 1.2392550854279274,
      "t_max_deploy_total": 1.2392550854279274,
      "k_search": 12,
      "uncovered_count": 18,
      "t_remaining_search": 0.423606797749979,
      "t_finish_search": 1.123606797749979,
      "bottleneck": "deploy"
    },
    "utility": 5.225147817000675e-05,
    "threshold": 0.024786146738121947,
    "decision": "reject"
  },
  {
    "time": 0.7,
    "proposal": "D7->T13",
    "baseline": {
      "makespan": 1.2393073369060974,
      "t_current": 0.7,
      "t_committed": 0.30000000000000004,
      "t_inevitable": 1.2393073369060974,
      "t_max_deploy_total": 1.2393073369060974,
      "k_search": 13,
      "uncovered_count": 18,
      "t_remaining_search": 0.423606797749979,
      "t_finish_search": 1.123606797749979,
      "bottleneck": "deploy"
    },
    "after_action": {
      "makespan": 1.2393073369060974,
      "t_current": 0.7,
      "t_committed": 1.2099019513592784,
      "t_inevitable": 1.2393073369060974,
      "t_max_deploy_total": 1.2393073369060974,
      "k_search": 12,
      "uncovered_count": 18,
      "t_remaining_search": 0.423606797749979,
      "t_finish_search": 1.123606797749979,
      "bottleneck": "deploy"
    },
    "utility": 0.0,
    "threshold": 0.024786146738121947,
    "decision": "reject"
  },
  {
    "time": 0.7,
    "proposal": "D4->T6",
    "baseline": {
      "makespan": 1.2393073369060974,
      "t_current": 0.7,
      "t_committed": 0.30000000000000004,
      "t_inevitable": 1.2393073369060974,
      "t_max_deploy_total": 1.2393073369060974,
      "k_search": 13,
      "uncovered_count": 18,
      "t_remaining_search": 0.423606797749979,
      "t_finish_search": 1.123606797749979,
      "bottleneck": "deploy"
    },
    "after_action": {
      "makespan": 1.2393073369060974,
      "t_current": 0.7,
      "t_committed": 1.2,
      "t_inevitable": 1.2393073369060974,
      "t_max_deploy_total": 1.2393073369060974,
      "k_search": 12,
      "uncovered_count": 18,
      "t_remaining_search": 0.423606797749979,
      "t_finish_search": 1.123606797749979,
      "bottleneck": "deploy"
    },
    "utility": 0.0,
    "threshold": 0.024786146738121947,
    "decision": "reject"
  },
  {
    "time": 0.7,
    "proposal": "D2->T10",
    "baseline": {
      "makespan": 1.2393073369060974,
      "t_current": 0.7,
      "t_committed": 0.30000000000000004,
      "t_inevitable": 1.2393073369060974,
      "t_max_deploy_total": 1.2393073369060974,
      "k_search": 13,
      "uncovered_count": 18,
      "t_remaining_search": 0.423606797749979,
      "t_finish_search": 1.123606797749979,
      "bottleneck": "deploy"
    },
    "after_action": {
      "makespan": 1.2385336230308797,
      "t_current": 0.7,
      "t_committed": 1.112310562561766,
      "t_inevitable": 1.2385336230308797,
      "t_max_deploy_total": 1.2385336230308797,
      "k_search": 12,
      "uncovered_count": 18,
      "t_remaining_search": 0.4559253948224816,
      "t_finish_search": 1.1559253948224817,
      "bottleneck": "deploy"
    },
    "utility": 0.0007737138752177408,
    "threshold": 0.024786146738121947,
    "decision": "reject"
  },
  {
    "time": 0.7,
    "proposal": "D0->T9",
    "baseline": {
      "makespan": 1.2393073369060974,
      "t_current": 0.7,
      "t_committed": 0.30000000000000004,
      "t_inevitable": 1.2393073369060974,
      "t_max_deploy_total": 1.2393073369060974,
      "k_search": 13,
      "uncovered_count": 18,
      "t_remaining_search": 0.423606797749979,
      "t_finish_search": 1.123606797749979,
      "bottleneck": "deploy"
    },
    "after_action": {
      "makespan": 1.2393073369060974,
      "t_current": 0.7,
      "t_committed": 1.0778604857374643,
      "t_inevitable": 1.2393073369060974,
      "t_max_deploy_total": 1.2393073369060974,
      "k_search": 12,
      "uncovered_count": 18,
      "t_remaining_search": 0.423606797749979,
      "t_finish_search": 1.123606797749979,
      "bottleneck": "deploy"
    },
    "utility": 0.0,
    "threshold": 0.024786146738121947,
    "decision": "reject"
  },
  {
    "time": 0.7,
    "proposal": "D8->T14",
    "baseline": {
      "makespan": 1.2393073369060974,
      "t_current": 0.7,
      "t_committed": 0.30000000000000004,
      "t_inevitable": 1.2393073369060974,
      "t_max_deploy_total": 1.2393073369060974,
      "k_search": 13,
      "uncovered_count": 18,
      "t_remaining_search": 0.423606797749979,
      "t_finish_search": 1.123606797749979,
      "bottleneck": "deploy"
    },
    "after_action": {
      "makespan": 1.2393073369060974,
      "t_current": 0.7,
      "t_committed": 0.9236067977499789,
      "t_inevitable": 1.2393073369060974,
      "t_max_deploy_total": 1.2393073369060974,
      "k_search": 12,
      "uncovered_count": 18,
      "t_remaining_search": 0.423606797749979,
      "t_finish_search": 1.123606797749979,
      "bottleneck": "deploy"
    },
    "utility": 0.0,
    "threshold": 0.024786146738121947,
    "decision": "reject"
  },
  {
    "time": 0.7,
    "proposal": "D5->T12",
    "baseline": {
      "makespan": 1.2393073369060974,
      "t_current": 0.7,
      "t_committed": 0.30000000000000004,
      "t_inevitable": 1.2393073369060974,
      "t_max_deploy_total": 1.2393073369060974,
      "k_search": 13,
      "uncovered_count": 18,
      "t_remaining_search": 0.423606797749979,
      "t_finish_search": 1.123606797749979,
      "bottleneck": "deploy"
    },
    "after_action": {
      "makespan": 1.2393073369060974,
      "t_current": 0.7,
      "t_committed": 0.7999999999999999,
      "t_inevitable": 1.2393073369060974,
      "t_max_deploy_total": 1.2393073369060974,
      "k_search": 12,
      "uncovered_count": 18,
      "t_remaining_search": 0.423606797749979,
      "t_finish_search": 1.123606797749979,
      "bottleneck": "deploy"
    },
    "utility": 0.0,
    "threshold": 0.024786146738121947,
    "decision": "reject"
  },
  {
    "time": 0.7999999999999999,
    "proposal": "D5->T7",
    "baseline": {
      "makespan": 1.5280109889280518,
      "t_current": 0.7999999999999999,
      "t_committed": 0.30000000000000004,
      "t_inevitable": 1.2476041167628125,
      "t_max_deploy_total": 1.2476041167628125,
      "k_search": 12,
      "uncovered_count": 10,
      "t_remaining_search": 0.7280109889280518,
      "t_finish_search": 1.5280109889280518,
      "bottleneck": "search"
    },
    "after_action": {
      "makespan": 1.5280109889280518,
      "t_current": 0.7999999999999999,
      "t_committed": 1.247213595499958,
      "t_inevitable": 1.2476041167628125,
      "t_max_deploy_total": 1.2476041167628125,
      "k_search": 11,
      "uncovered_count": 10,
      "t_remaining_search": 0.7280109889280518,
      "t_finish_search": 1.5280109889280518,
      "bottleneck": "search"
    },
    "utility": 0.0,
    "threshold": 0.030560219778561035,
    "decision": "reject"
  },
  {
    "time": 0.7999999999999999,
    "proposal": "D9->T6",
    "baseline": {
      "makespan": 1.5280109889280518,
      "t_current": 0.7999999999999999,
      "t_committed": 0.30000000000000004,
      "t_inevitable": 1.2476041167628125,
      "t_max_deploy_total": 1.2476041167628125,
      "k_search": 12,
      "uncovered_count": 10,
      "t_remaining_search": 0.7280109889280518,
      "t_finish_search": 1.5280109889280518,
      "bottleneck": "search"
    },
    "after_action": {
      "makespan": 1.5280109889280518,
      "t_current": 0.7999999999999999,
      "t_committed": 1.247213595499958,
      "t_inevitable": 1.2476041167628125,
      "t_max_deploy_total": 1.2476041167628125,
      "k_search": 11,
      "uncovered_count": 10,
      "t_remaining_search": 0.7280109889280518,
      "t_finish_search": 1.5280109889280518,
      "bottleneck": "search"
    },
    "utility": 0.0,
    "threshold": 0.030560219778561035,
    "decision": "reject"
  },
  {
    "time": 0.7999999999999999,
    "proposal": "D10->T0",
    "baseline": {
      "makespan": 1.5280109889280518,
      "t_current": 0.7999999999999999,
      "t_committed": 0.30000000000000004,
      "t_inevitable": 1.2476041167628125,
      "t_max_deploy_total": 1.2476041167628125,
      "k_search": 12,
      "uncovered_count": 10,
      "t_remaining_search": 0.7280109889280518,
      "t_finish_search": 1.5280109889280518,
      "bottleneck": "search"
    },
    "after_action": {
      "makespan": 1.5280109889280518,
      "t_current": 0.7999999999999999,
      "t_committed": 1.247213595499958,
      "t_inevitable": 1.1180599447407458,
      "t_max_deploy_total": 1.247213595499958,
      "k_search": 11,
      "uncovered_count": 10,
      "t_remaining_search": 0.7280109889280518,
      "t_finish_search": 1.5280109889280518,
      "bottleneck": "search"
    },
    "utility": 0.0,
    "threshold": 0.030560219778561035,
    "decision": "reject"
  },
  {
    "time": 0.7999999999999999,
    "proposal": "D2->T14",
    "baseline": {
      "makespan": 1.5280109889280518,
      "t_current": 0.7999999999999999,
      "t_committed": 0.30000000000000004,
      "t_inevitable": 1.2476041167628125,
      "t_max_deploy_total": 1.2476041167628125,
      "k_search": 12,
      "uncovered_count": 10,
      "t_remaining_search": 0.7280109889280518,
      "t_finish_search": 1.5280109889280518,
      "bottleneck": "search"
    },
    "after_action": {
      "makespan": 1.3099019513592784,
      "t_current": 0.7999999999999999,
      "t_committed": 1.2242640687119284,
      "t_inevitable": 1.2477787656987502,
      "t_max_deploy_total": 1.2477787656987502,
      "k_search": 11,
      "uncovered_count": 10,
      "t_remaining_search": 0.5099019513592784,
      "t_finish_search": 1.3099019513592784,
      "bottleneck": "search"
    },
    "utility": 0.2181090375687733,
    "threshold": 0.030560219778561035,
    "decision": "accept"
  },
  {
    "time": 0.7999999999999999,
    "proposal": "D13->T12",
    "baseline": {
      "makespan": 1.5280109889280518,
      "t_current": 0.7999999999999999,
      "t_committed": 0.30000000000000004,
      "t_inevitable": 1.2476041167628125,
      "t_max_deploy_total": 1.2476041167628125,
      "k_search": 12,
      "uncovered_count": 10,
      "t_remaining_search": 0.7280109889280518,
      "t_finish_search": 1.5280109889280518,
      "bottleneck": "search"
    },
    "after_action": {
      "makespan": 1.3385164807134502,
      "t_current": 0.7999999999999999,
      "t_committed": 1.2242640687119284,
      "t_inevitable": 1.2477787656987502,
      "t_max_deploy_total": 1.2477787656987502,
      "k_search": 10,
      "uncovered_count": 10,
      "t_remaining_search": 0.5385164807134504,
      "t_finish_search": 1.3385164807134502,
      "bottleneck": "search"
    },
    "utility": -0.028614529354171747,
    "threshold": 0.02619803902718557,
    "decision": "reject"
  },
  {
    "time": 0.7999999999999999,
    "proposal": "D4->T2",
    "baseline": {
      "makespan": 1.5280109889280518,
      "t_current": 0.7999999999999999,
      "t_committed": 0.30000000000000004,
      "t_inevitable": 1.2476041167628125,
      "t_max_deploy_total": 1.2476041167628125,
      "k_search": 12,
      "uncovered_count": 10,
      "t_remaining_search": 0.7280109889280518,
      "t_finish_search": 1.5280109889280518,
      "bottleneck": "search"
    },
    "after_action": {
      "makespan": 1.2477787656987502,
      "t_current": 0.7999999999999999,
      "t_committed": 1.2242640687119284,
      "t_inevitable": 1.2477787656987502,
      "t_max_deploy_total": 1.2477787656987502,
      "k_search": 10,
      "uncovered_count": 10,
      "t_remaining_search": 0.31622776601683794,
      "t_finish_search": 1.1162277660168378,
      "bottleneck": "deploy"
    },
    "utility": 0.06212318566052821,
    "threshold": 0.02619803902718557,
    "decision": "accept"
  },
  {
    "time": 0.7999999999999999,
    "proposal": "D7->T9",
    "baseline": {
      "makespan": 1.5280109889280518,
      "t_current": 0.7999999999999999,
      "t_committed": 0.30000000000000004,
      "t_inevitable": 1.2476041167628125,
      "t_max_deploy_total": 1.2476041167628125,
      "k_search": 12,
      "uncovered_count": 10,
      "t_remaining_search": 0.7280109889280518,
      "t_finish_search": 1.5280109889280518,
      "bottleneck": "search"
    },
    "after_action": {
      "makespan": 1.2477787656987502,
      "t_current": 0.7999999999999999,
      "t_committed": 1.2242640687119284,
      "t_inevitable": 1.2477787656987502,
      "t_max_deploy_total": 1.2477787656987502,
      "k_search": 9,
      "uncovered_count": 10,
      "t_remaining_search": 0.31622776601683794,
      "t_finish_search": 1.1162277660168378,
      "bottleneck": "deploy"
    },
    "utility": 0.0,
    "threshold": 0.024955575313975006,
    "decision": "reject"
  },
  {
    "time": 0.7999999999999999,
    "proposal": "D3->T5",
    "baseline": {
      "makespan": 1.5280109889280518,
      "t_current": 0.7999999999999999,
      "t_committed": 0.30000000000000004,
      "t_inevitable": 1.2476041167628125,
      "t_max_deploy_total": 1.2476041167628125,
      "k_search": 12,
      "uncovered_count": 10,
      "t_remaining_search": 0.7280109889280518,
      "t_finish_search": 1.5280109889280518,
      "bottleneck": "search"
    },
    "after_action": {
      "makespan": 1.2477787656987502,
      "t_current": 0.7999999999999999,
      "t_committed": 1.2242640687119284,
      "t_inevitable": 1.2477787656987502,
      "t_max_deploy_total": 1.2477787656987502,
      "k_search": 9,
      "uncovered_count": 10,
      "t_remaining_search": 0.31622776601683794,
      "t_finish_search": 1.1162277660168378,
      "bottleneck": "deploy"
    },
    "utility": 0.0,
    "threshold": 0.024955575313975006,
    "decision": "reject"
  },
  {
    "time": 0.7999999999999999,
    "proposal": "D0->T1",
    "baseline": {
      "makespan": 1.5280109889280518,
      "t_current": 0.7999999999999999,
      "t_committed": 0.30000000000000004,
      "t_inevitable": 1.2476041167628125,
      "t_max_deploy_total": 1.2476041167628125,
      "k_search": 12,
      "uncovered_count": 10,
      "t_remaining_search": 0.7280109889280518,
      "t_finish_search": 1.5280109889280518,
      "bottleneck": "search"
    },
    "after_action": {
      "makespan": 1.2474564138421165,
      "t_current": 0.7999999999999999,
      "t_committed": 1.2242640687119284,
      "t_inevitable": 1.2474564138421165,
      "t_max_deploy_total": 1.2474564138421165,
      "k_search": 9,
      "uncovered_count": 10,
      "t_remaining_search": 0.31622776601683794,
      "t_finish_search": 1.1162277660168378,
      "bottleneck": "deploy"
    },
    "utility": 0.0003223518566337624,
    "threshold": 0.024955575313975006,
    "decision": "reject"
  },
  {
    "time": 0.7999999999999999,
    "proposal": "D11->T13",
    "baseline": {
      "makespan": 1.5280109889280518,
      "t_current": 0.7999999999999999,
      "t_committed": 0.30000000000000004,
      "t_inevitable": 1.2476041167628125,
      "t_max_deploy_total": 1.2476041167628125,
      "k_search": 12,
      "uncovered_count": 10,
      "t_remaining_search": 0.7280109889280518,
      "t_finish_search": 1.5280109889280518,
      "bottleneck": "search"
    },
    "after_action": {
      "makespan": 1.3099019513592784,
      "t_current": 0.7999999999999999,
      "t_committed": 1.2242640687119284,
      "t_inevitable": 1.2477787656987502,
      "t_max_deploy_total": 1.2477787656987502,
      "k_search": 9,
      "uncovered_count": 10,
      "t_remaining_search": 0.5099019513592784,
      "t_finish_search": 1.3099019513592784,
      "bottleneck": "search"
    },
    "utility": -0.06212318566052821,
    "threshold": 0.024955575313975006,
    "decision": "reject"
  },
  {
    "time": 0.7999999999999999,
    "proposal": "D14->T10",
    "baseline": {
      "makespan": 1.5280109889280518,
      "t_current": 0.7999999999999999,
      "t_committed": 0.30000000000000004,
      "t_inevitable": 1.2476041167628125,
      "t_max_deploy_total": 1.2476041167628125,
      "k_search": 12,
      "uncovered_count": 10,
      "t_remaining_search": 0.7280109889280518,
      "t_finish_search": 1.5280109889280518,
      "bottleneck": "search"
    },
    "after_action": {
      "makespan": 1.2477787656987502,
      "t_current": 0.7999999999999999,
      "t_committed": 1.2242640687119284,
      "t_inevitable": 1.2477787656987502,
      "t_max_deploy_total": 1.2477787656987502,
      "k_search": 9,
      "uncovered_count": 10,
      "t_remaining_search": 0.31622776601683794,
      "t_finish_search": 1.1162277660168378,
      "bottleneck": "deploy"
    },
    "utility": 0.0,
    "threshold": 0.024955575313975006,
    "decision": "reject"
  }
]